mokr/__init__.py
mokr/browser/__init__.py
mokr/browser/browser.py
mokr/browser/console.py
mokr/browser/context.py
mokr/browser/page.py
mokr/browser/target.py
mokr/browser/viewport.py
mokr/browser/worker.py
mokr/connection/__init__.py
mokr/connection/base.py
mokr/connection/connection.py
mokr/connection/devtools.py
mokr/console.py
mokr/constants/__init__.py
mokr/constants/events.py
mokr/constants/http.py
mokr/constants/info.py
mokr/constants/javascript/__init__.py
mokr/constants/javascript/add_binding.js
mokr/constants/javascript/element_in_view.js
mokr/constants/javascript/embed_js.js
mokr/constants/javascript/embed_js_url.js
mokr/constants/javascript/embed_style.js
mokr/constants/javascript/embed_style_url.js
mokr/constants/javascript/evaluate_xpath.js
mokr/constants/javascript/fetch_request.js
mokr/constants/javascript/get_binding_result.js
mokr/constants/javascript/get_content.js
mokr/constants/javascript/get_property.js
mokr/constants/javascript/scroll_into_view.js
mokr/constants/javascript/select_values.js
mokr/constants/javascript/set_content.js
mokr/constants/javascript/wait_for_node.js
mokr/constants/javascript/wait_for_page.js
mokr/constants/keys.py
mokr/constants/typing.py
mokr/download.py
mokr/exceptions.py
mokr/execution/__init__.py
mokr/execution/context.py
mokr/execution/handle/__init__.py
mokr/execution/handle/element.py
mokr/execution/handle/javascript.py
mokr/frame/__init__.py
mokr/frame/frame.py
mokr/frame/manager.py
mokr/frame/wait.py
mokr/input/__init__.py
mokr/input/dialog.py
mokr/input/keyboard.py
mokr/input/mouse.py
mokr/input/touchscreen.py
mokr/launch/__init__.py
mokr/launch/base.py
mokr/launch/chrome.py
mokr/launch/firefox.py
mokr/network/__init__.py
mokr/network/event.py
mokr/network/extensions/ffauth/background.js
mokr/network/extensions/ffauth/manifest.json
mokr/network/fetch.py
mokr/network/http.py
mokr/network/manager/__init__.py
mokr/network/manager/base.py
mokr/network/manager/chrome.py
mokr/network/manager/firefox.py
mokr-0.1.2.dist-info/entry_points.txt
mokr-0.1.2.dist-info/LICENSE
mokr-0.1.2.dist-info/METADATA
mokr-0.1.2.dist-info/WHEEL
mokr-0.1.2.dist-info/RECORD
